addecli-0.8.2.dist-info/METADATA
addecli-0.8.2.dist-info/WHEEL
addecli-0.8.2.dist-info/entry_points.txt
addecli/__main__.py
addecli/cli_commands.py
addecli/create.py
addecli/init_project/.gitignore
addecli/init_project/.pre-commit-config.yaml
addecli/init_project/conftest.py
addecli/init_project/log-config.yml
addecli/init_project/scripts/create/__main__.py
addecli/init_project/src/config.py
addecli/init_project/src/main/app/__init__.py
addecli/init_project/src/metadata/__init__.py
addecli/init_project/src/metadata/_extras.py
addecli-0.8.2.dist-info/RECORD
