Metadata-Version: 2.1
Name: addecli
Version: 0.8.2
Summary: Default template for PDM package
Author-Email: Victor <victordeonroyale@gmail.com>
License: MIT
Requires-Python: >=3.11
Requires-Dist: typer>=0.12.3
Requires-Dist: pdm>=2.15.2
